silverflaghwdata/__init__.py
silverflaghwdata/client.py
silverflaghwdata/clientmng.py
silverflaghwdata/debug.py
silverflaghwdata/main.py
silverflaghwdata/manager.py
silverflaghwdata/server.py
silverflaghwdata/settings.py
silverflaghwdata/srvmng.py
silverflaghwdata/states/__init__.py
silverflaghwdata/states/alabama.py
silverflaghwdata/states/alaska.py
silverflaghwdata/states/arizona.py
silverflaghwdata/states/arkansas.py
silverflaghwdata/states/california.py
silverflaghwdata/states/colorado.py
silverflaghwdata/states/connecticut.py
silverflaghwdata/states/deleware.py
silverflaghwdata/states/florida.py
silverflaghwdata/states/georgia.py
silverflaghwdata/states/idaho.py
silverflaghwdata/states/illinois.py
silverflaghwdata/states/indiana.py
silverflaghwdata/states/iowa.py
silverflaghwdata/states/kansas.py
silverflaghwdata/states/kentucky.py
silverflaghwdata/states/louisiana.py
silverflaghwdata/states/maine.py
silverflaghwdata/states/maryland.py
silverflaghwdata/states/massachusetts.py
silverflaghwdata/states/michigan.py
silverflaghwdata/states/minnesota.py
silverflaghwdata/states/mississippi.py
silverflaghwdata-0.1.14.dist-info/licenses/LICENSE
silverflaghwdata-0.1.14.dist-info/METADATA
silverflaghwdata-0.1.14.dist-info/WHEEL
silverflaghwdata-0.1.14.dist-info/entry_points.txt
silverflaghwdata-0.1.14.dist-info/top_level.txt
silverflaghwdata-0.1.14.dist-info/RECORD
