Metadata-Version: 2.4
Name: silverflaghwdata
Version: 0.1.14
Summary: Scrapers for all of the DoT websites.
Author-email: SilverFlag <contact@silverflag.net>
License-File: LICENSE
Dynamic: license-file
